takolib/__init__.py
takolib/hello.py
takolib-0.0.1.dist-info/LICENSE
takolib-0.0.1.dist-info/METADATA
takolib-0.0.1.dist-info/WHEEL
takolib-0.0.1.dist-info/top_level.txt
takolib-0.0.1.dist-info/RECORD
