Metadata-Version: 2.1
Name: takolib
Version: 0.0.1
Summary: Currently for testing purposes
Home-page: https://github.com/Tqkoyaki/TakoLib
Author: Takoyaki (Nikhil Pandey)
Author-email: np768@scarletmail.rutgers.edu
Classifier: Programming Language :: Python :: 3
Classifier: License :: OSI Approved :: MIT License
Classifier: Operating System :: OS Independent
Requires-Python: >=3.7
License-File: LICENSE
